uamutils/__init__.py
uamutils/blocks.py
uamutils/config.py
uamutils/data.py
uamutils/mod4.py
uamutils/shared.py
uamutils-0.0.0a3.dist-info/LICENSE.txt
uamutils-0.0.0a3.dist-info/METADATA
uamutils-0.0.0a3.dist-info/WHEEL
uamutils-0.0.0a3.dist-info/top_level.txt
uamutils-0.0.0a3.dist-info/RECORD
